{".class":"MypyFile","_fullname":"azure.ai.ml.constants._job.pipeline","future_import_flags":[],"is_partial_stub_package":false,"is_stub":false,"names":{".class":"SymbolTable","COMPONENT_IO_KEYWORDS":{".class":"SymbolTableNode","kind":"Gdef","node":{".class":"Var","flags":["is_inferred","has_explicit_value"],"fullname":"azure.ai.ml.constants._job.pipeline.COMPONENT_IO_KEYWORDS","name":"COMPONENT_IO_KEYWORDS","type":{".class":"Instance","args":["builtins.str"],"extra_attrs":null,"type_ref":"builtins.set"}}},"PipelineConstants":{".class":"SymbolTableNode","kind":"Gdef","node":{".class":"TypeInfo","_promote":[],"abstract_attributes":[],"alt_promote":null,"bases":["builtins.object"],"dataclass_transform_spec":null,"declared_metaclass":null,"defn":{".class":"ClassDef","fullname":"azure.ai.ml.constants._job.pipeline.PipelineConstants","name":"PipelineConstants","type_vars":[]},"deletable_attributes":[],"deprecated":null,"flags":[],"fullname":"azure.ai.ml.constants._job.pipeline.PipelineConstants","has_param_spec_type":false,"metaclass_type":null,"metadata":{},"module_name":"azure.ai.ml.constants._job.pipeline","mro":["azure.ai.ml.constants._job.pipeline.PipelineConstants","builtins.object"],"names":{".class":"SymbolTable","CODE":{".class":"SymbolTableNode","kind":"Mdef","node":{".class":"Var","flags":["is_initialized_in_class","is_ready","is_inferred","has_explicit_value"],"fullname":"azure.ai.ml.constants._job.pipeline.PipelineConstants.CODE","name":"CODE","type":"builtins.str"}},"CONTINUE_ON_STEP_FAILURE":{".class":"SymbolTableNode","kind":"Mdef","node":{".class":"Var","flags":["is_initialized_in_class","is_ready","is_inferred","has_explicit_value"],"fullname":"azure.ai.ml.constants._job.pipeline.PipelineConstants.CONTINUE_ON_STEP_FAILURE","name":"CONTINUE_ON_STEP_FAILURE","type":"builtins.str"}},"CONTINUE_RUN_ON_FAILED_OPTIONAL_INPUT":{".class":"SymbolTableNode","kind":"Mdef","node":{".class":"Var","flags":["is_initialized_in_class","is_ready","is_inferred","has_explicit_value"],"fullname":"azure.ai.ml.constants._job.pipeline.PipelineConstants.CONTINUE_RUN_ON_FAILED_OPTIONAL_INPUT","name":"CONTINUE_RUN_ON_FAILED_OPTIONAL_INPUT","type":"builtins.str"}},"DATASTORE_REST":{".class":"SymbolTableNode","kind":"Mdef","node":{".class":"Var","flags":["is_initialized_in_class","is_ready","is_inferred","has_explicit_value"],"fullname":"azure.ai.ml.constants._job.pipeline.PipelineConstants.DATASTORE_REST","name":"DATASTORE_REST","type":"builtins.str"}},"DEFAULT_COMPUTE":{".class":"SymbolTableNode","kind":"Mdef","node":{".class":"Var","flags":["is_initialized_in_class","is_ready","is_inferred","has_explicit_value"],"fullname":"azure.ai.ml.constants._job.pipeline.PipelineConstants.DEFAULT_COMPUTE","name":"DEFAULT_COMPUTE","type":"builtins.str"}},"DEFAULT_DATASTORE":{".class":"SymbolTableNode","kind":"Mdef","node":{".class":"Var","flags":["is_initialized_in_class","is_ready","is_inferred","has_explicit_value"],"fullname":"azure.ai.ml.constants._job.pipeline.PipelineConstants.DEFAULT_DATASTORE","name":"DEFAULT_DATASTORE","type":"builtins.str"}},"DEFAULT_DATASTORE_REST":{".class":"SymbolTableNode","kind":"Mdef","node":{".class":"Var","flags":["is_initialized_in_class","is_ready","is_inferred","has_explicit_value"],"fullname":"azure.ai.ml.constants._job.pipeline.PipelineConstants.DEFAULT_DATASTORE_REST","name":"DEFAULT_DATASTORE_REST","type":"builtins.str"}},"DEFAULT_DATASTORE_SDK":{".class":"SymbolTableNode","kind":"Mdef","node":{".class":"Var","flags":["is_initialized_in_class","is_ready","is_inferred","has_explicit_value"],"fullname":"azure.ai.ml.constants._job.pipeline.PipelineConstants.DEFAULT_DATASTORE_SDK","name":"DEFAULT_DATASTORE_SDK","type":"builtins.str"}},"ENVIRONMENT":{".class":"SymbolTableNode","kind":"Mdef","node":{".class":"Var","flags":["is_initialized_in_class","is_ready","is_inferred","has_explicit_value"],"fullname":"azure.ai.ml.constants._job.pipeline.PipelineConstants.ENVIRONMENT","name":"ENVIRONMENT","type":"builtins.str"}},"PIPELINE_JOB_TYPE":{".class":"SymbolTableNode","kind":"Mdef","node":{".class":"Var","flags":["is_initialized_in_class","is_ready","is_inferred","has_explicit_value"],"fullname":"azure.ai.ml.constants._job.pipeline.PipelineConstants.PIPELINE_JOB_TYPE","name":"PIPELINE_JOB_TYPE","type":"builtins.str"}},"REUSED_FLAG_FIELD":{".class":"SymbolTableNode","kind":"Mdef","node":{".class":"Var","flags":["is_initialized_in_class","is_ready","is_inferred","has_explicit_value"],"fullname":"azure.ai.ml.constants._job.pipeline.PipelineConstants.REUSED_FLAG_FIELD","name":"REUSED_FLAG_FIELD","type":"builtins.str"}},"REUSED_FLAG_TRUE":{".class":"SymbolTableNode","kind":"Mdef","node":{".class":"Var","flags":["is_initialized_in_class","is_ready","is_inferred","has_explicit_value"],"fullname":"azure.ai.ml.constants._job.pipeline.PipelineConstants.REUSED_FLAG_TRUE","name":"REUSED_FLAG_TRUE","type":"builtins.str"}},"REUSED_JOB_ID":{".class":"SymbolTableNode","kind":"Mdef","node":{".class":"Var","flags":["is_initialized_in_class","is_ready","is_inferred","has_explicit_value"],"fullname":"azure.ai.ml.constants._job.pipeline.PipelineConstants.REUSED_JOB_ID","name":"REUSED_JOB_ID","type":"builtins.str"}}},"self_type":{".class":"TypeVarType","default":{".class":"AnyType","missing_import_name":null,"source_any":null,"type_of_any":4},"fullname":"azure.ai.ml.constants._job.pipeline.PipelineConstants.Self","id":0,"name":"Self","namespace":"","upper_bound":"azure.ai.ml.constants._job.pipeline.PipelineConstants","values":[],"variance":0},"slots":null,"tuple_type":null,"type_vars":[],"typeddict_type":null}},"ValidationErrorCode":{".class":"SymbolTableNode","kind":"Gdef","node":{".class":"TypeInfo","_promote":[],"abstract_attributes":[],"alt_promote":null,"bases":["builtins.object"],"dataclass_transform_spec":null,"declared_metaclass":null,"defn":{".class":"ClassDef","fullname":"azure.ai.ml.constants._job.pipeline.ValidationErrorCode","name":"ValidationErrorCode","type_vars":[]},"deletable_attributes":[],"deprecated":null,"flags":[],"fullname":"azure.ai.ml.constants._job.pipeline.ValidationErrorCode","has_param_spec_type":false,"metaclass_type":null,"metadata":{},"module_name":"azure.ai.ml.constants._job.pipeline","mro":["azure.ai.ml.constants._job.pipeline.ValidationErrorCode","builtins.object"],"names":{".class":"SymbolTable","PARAMETER_TYPE_UNKNOWN":{".class":"SymbolTableNode","kind":"Mdef","node":{".class":"Var","flags":["is_initialized_in_class","is_ready","is_inferred","has_explicit_value"],"fullname":"azure.ai.ml.constants._job.pipeline.ValidationErrorCode.PARAMETER_TYPE_UNKNOWN","name":"PARAMETER_TYPE_UNKNOWN","type":"builtins.str"}}},"self_type":{".class":"TypeVarType","default":{".class":"AnyType","missing_import_name":null,"source_any":null,"type_of_any":4},"fullname":"azure.ai.ml.constants._job.pipeline.ValidationErrorCode.Self","id":0,"name":"Self","namespace":"","upper_bound":"azure.ai.ml.constants._job.pipeline.ValidationErrorCode","values":[],"variance":0},"slots":null,"tuple_type":null,"type_vars":[],"typeddict_type":null}},"__annotations__":{".class":"SymbolTableNode","kind":"Gdef","node":{".class":"Var","flags":["is_ready"],"fullname":"azure.ai.ml.constants._job.pipeline.__annotations__","name":"__annotations__","type":{".class":"Instance","args":["builtins.str",{".class":"AnyType","missing_import_name":null,"source_any":null,"type_of_any":6}],"extra_attrs":null,"type_ref":"builtins.dict"}}},"__doc__":{".class":"SymbolTableNode","kind":"Gdef","node":{".class":"Var","flags":["is_ready"],"fullname":"azure.ai.ml.constants._job.pipeline.__doc__","name":"__doc__","type":"builtins.str"}},"__file__":{".class":"SymbolTableNode","kind":"Gdef","node":{".class":"Var","flags":["is_ready"],"fullname":"azure.ai.ml.constants._job.pipeline.__file__","name":"__file__","type":"builtins.str"}},"__name__":{".class":"SymbolTableNode","kind":"Gdef","node":{".class":"Var","flags":["is_ready"],"fullname":"azure.ai.ml.constants._job.pipeline.__name__","name":"__name__","type":"builtins.str"}},"__package__":{".class":"SymbolTableNode","kind":"Gdef","node":{".class":"Var","flags":["is_ready"],"fullname":"azure.ai.ml.constants._job.pipeline.__package__","name":"__package__","type":"builtins.str"}},"__spec__":{".class":"SymbolTableNode","kind":"Gdef","node":{".class":"Var","flags":["is_ready"],"fullname":"azure.ai.ml.constants._job.pipeline.__spec__","name":"__spec__","type":"_frozen_importlib.ModuleSpec"}}},"path":"C:\\Users\\bsean\\AppData\\Local\\Packages\\PythonSoftwareFoundation.Python.3.13_qbz5n2kfra8p0\\LocalCache\\local-packages\\Python313\\site-packages\\azure\\ai\\ml\\constants\\_job\\pipeline.py"}